airflow_extended_metrics/__init__.py
airflow_extended_metrics/airflow_plugins/__init__.py
airflow_extended_metrics/airflow_plugins/monitoring_operators.py
airflow_extended_metrics/helpers/__init__.py
airflow_extended_metrics/helpers/stackdriver_metrics.py
tests/__init__.py
tests/dag_testing_stackdriver.py
tests/test_stackdriver_monitoring.py
airflow_extended_metrics-0.1.1.dist-info/LICENSE
airflow_extended_metrics-0.1.1.dist-info/METADATA
airflow_extended_metrics-0.1.1.dist-info/WHEEL
airflow_extended_metrics-0.1.1.dist-info/entry_points.txt
airflow_extended_metrics-0.1.1.dist-info/top_level.txt
airflow_extended_metrics-0.1.1.dist-info/RECORD
