Metadata-Version: 2.1
Name: airflow-extended-metrics
Version: 0.1.1
Summary: Package to expand Airflow for custom metrics.
Home-page: https://github.com/nytm/airflow-extended-metrics
Author: Sarah Duncan
Author-email: sarah.duncan@nytimes.com
License: MIT
Platform: UNKNOWN
Requires-Dist: tzlocal (<2.0.0.0,>=1.5.0.0)
Requires-Dist: apache-airflow (==1.10.1)
Requires-Dist: google-cloud-monitoring (==0.31.1)
